{
  "carousel":[
      {
        "id":1,
        "img":"https://i.postimg.cc/Dz64FtkH/carrousel1.png"
      },
      {
        "id":2,
        "img":"https://i.postimg.cc/Y9y4LYSx/carrousel2.png"
      },
      {
        "id":3,
        "img":"https://i.postimg.cc/cHJgJXdH/carrousel3.png"
      }
  ],
  "cards":[
    {
      "titulo": "Hamburguesa Inglesa",
      "imagen": "https://i.postimg.cc/hvF3bv7Y/Hamburguesa-a-la-Inglesa.png",
      "descripción": "Hamburguesa clásica con queso cheddar y salsa Worcestershire.",
      "price": "6.00€"
    },
    {
      "titulo": "Hamburguesa de Bacon",
      "imagen": "https://i.postimg.cc/dVnpPJz7/Hamburguesa-Bacon.png",
      "descripción": "Hamburguesa con tocino y queso cheddar derretido.",
      "price": "5.00€"
    },
    {
      "titulo": "Hamburguesa Clasica",
      "imagen": "https://i.postimg.cc/pT56Fzy8/Hamburguesa-Clasica.png",
      "descripción": "Hamburguesa simple con lechuga, tomate y cebolla.",
      "price": "4.50€"
    },
    {
      "titulo": "Hamburguesa de Medio Kilo",
      "imagen": "https://i.postimg.cc/SRW1Z46x/Hamburguesa-Medio-Kilo.png",
      "descripción": "Hamburguesa grande de 500 gramos.",
      "price": "8.50€"
    },
    {
      "titulo": "Hamburguesa Triple",
      "imagen": "https://i.postimg.cc/0NB4jc5P/Hamburguesa-Triple.png",
      "descripción": "Hamburguesa con tres carnes, queso, tocino y vegetales.",
      "price": "9.50€"
    },
    {
      "titulo": "Hamburguesa Vegana",
      "imagen": "https://i.postimg.cc/tgTf9LjB/Hamburguesa-Vegana.png",
      "descripción": "Hamburguesa vegetariana hecha con ingredientes de origen vegetal.",
      "price": "4.00€"
    },
    {
      "titulo": "Hamburguesa Gourmet",
      "imagen": "https://i.postimg.cc/BvWsq517/Hamburguesa-Gourmet.png",
      "descripción": "Hamburguesa con ingredientes especiales y sofisticados.",
      "price": "10.00€"
    },
    {
      "titulo": "Hamburguesa Alemana",
      "imagen": "https://i.postimg.cc/GmTdwg9s/Hamburguesa-Alemana.png",
      "descripción": "Hamburguesa con queso emmental y salsa de mostaza alemana.",
      "price": "5.50€"
    }
  ]
}